odoo/addons/account_peppol_send_format_odoo/README.rst
odoo/addons/account_peppol_send_format_odoo/__init__.py
odoo/addons/account_peppol_send_format_odoo/__manifest__.py
odoo/addons/account_peppol_send_format_odoo/models/__init__.py
odoo/addons/account_peppol_send_format_odoo/models/account_edi_xml_ubl_bis3.py
odoo/addons/account_peppol_send_format_odoo/readme/CONTRIBUTORS.md
odoo/addons/account_peppol_send_format_odoo/readme/CREDITS.md
odoo/addons/account_peppol_send_format_odoo/readme/DESCRIPTION.md
odoo/addons/account_peppol_send_format_odoo/static/description/icon.png
odoo/addons/account_peppol_send_format_odoo/static/description/index.html
odoo/addons/account_peppol_send_format_odoo/wizard/__init__.py
odoo/addons/account_peppol_send_format_odoo/wizard/account_invoice_send.py
odoo_addon_account_peppol_send_format_odoo-16.0.1.0.0.3.dist-info/METADATA
odoo_addon_account_peppol_send_format_odoo-16.0.1.0.0.3.dist-info/WHEEL
odoo_addon_account_peppol_send_format_odoo-16.0.1.0.0.3.dist-info/top_level.txt
odoo_addon_account_peppol_send_format_odoo-16.0.1.0.0.3.dist-info/RECORD
